ix_f_scraper/ASNInfo.py
ix_f_scraper/__init__.py
ix_f_scraper/cli.py
ix_f_scraper/csvWrite.py
ix_f_scraper/ix_f_scraper.py
ix_f_scraper/macLookup.py
ix_f_scraper-0.0.6.dist-info/AUTHORS.rst
ix_f_scraper-0.0.6.dist-info/LICENSE
ix_f_scraper-0.0.6.dist-info/METADATA
ix_f_scraper-0.0.6.dist-info/WHEEL
ix_f_scraper-0.0.6.dist-info/entry_points.txt
ix_f_scraper-0.0.6.dist-info/top_level.txt
ix_f_scraper-0.0.6.dist-info/RECORD
