Metadata-Version: 2.1
Name: ix-f-scraper
Version: 0.0.6
Summary: IX-F Scraper
Home-page: https://github.com/as207960/ix-f-scraper
Author: Alfie Foster
Author-email: bonzi@as207960.net
License: MIT license
Keywords: ix_f_scraper
Platform: UNKNOWN
Classifier: Development Status :: 2 - Pre-Alpha
Classifier: Intended Audience :: Developers
Classifier: License :: OSI Approved :: MIT License
Classifier: Natural Language :: English
Classifier: Programming Language :: Python :: 3.8
Requires-Python: >=3.8
Requires-Dist: Click (>=7.0)
Requires-Dist: networktoolkit
